{
    "solution": {
        "resourceNameSuffix": "c481a5",
        "resourceGroupName": "helly09180952-rg",
        "tenantId": "72f988bf-86f1-41af-91ab-2d7cd011db47",
        "subscriptionId": "1756abc0-3554-4341-8d6a-46674962ea19",
        "subscriptionName": "Teams Cloud - Dev Test with TTL = 7 Days",
        "location": "East US",
        "teamsAppTenantId": "{{solution.teamsAppTenantId}}",
        "remoteTeamsAppId": "e22babe7-fd18-48e6-acef-d933089ba748",
        "provisionSucceeded": true
    },
    "fx-resource-frontend-hosting": {
        "storageName": "helly09180952fec481a5",
        "endpoint": "https://helly09180952fec481a5.z13.web.core.windows.net",
        "domain": "helly09180952fec481a5.z13.web.core.windows.net"
    },
    "fx-resource-identity": {
        "identityName": "/subscriptions/1756abc0-3554-4341-8d6a-46674962ea19/resourcegroups/helly09180952-rg/providers/Microsoft.ManagedIdentity/userAssignedIdentities/helly09180952-msi-c481a5",
        "identityId": "6061d08c-151a-42ed-84a1-9bb77c5ab338",
        "identity": "helly09180952-msi-c481a5"
    },
    "fx-resource-azure-sql": {
        "skipAddingUser": true,
        "admin": "helly",
        "sqlEndpoint": "helly09180952-sql-c481a5.database.windows.net",
        "databaseName": "helly09180952-db-c481a5"
    },
    "fx-resource-bot": {
        "skuName": "B1",
        "siteName": "helly09180952btc481a5",
        "botId": "eb8f770c-8fc5-49e8-943a-720c84dad226",
        "botPassword": "{{fx-resource-bot.botPassword}}",
        "objectId": "a4956ad9-11a3-448f-875e-c94519ea4897",
        "validDomain": "helly09180952btc481a5.azurewebsites.net",
        "appServicePlan": "helly09180952btc481a5",
        "botChannelReg": "helly09180952btc481a5",
        "siteEndpoint": "https://helly09180952btc481a5.azurewebsites.net"
    },
    "fx-resource-aad-app-for-teams": {
        "clientId": "897161e9-9154-412f-88d6-f9ed19d41b4c",
        "clientSecret": "{{fx-resource-aad-app-for-teams.clientSecret}}",
        "objectId": "8b533e43-8af7-43bf-b37f-5d5b2e4f4d15",
        "oauth2PermissionScopeId": "9607d3e4-d045-4c68-b455-951d5142afd7",
        "tenantId": "b78ae59c-3ebf-4705-85d6-7283f2cd47f9",
        "oauthHost": "https://login.microsoftonline.com",
        "oauthAuthority": "https://login.microsoftonline.com/b78ae59c-3ebf-4705-85d6-7283f2cd47f9",
        "applicationIdUris": "api://helly09180952fec481a5.z13.web.core.windows.net/botid-eb8f770c-8fc5-49e8-943a-720c84dad226"
    },
    "fx-resource-function": {
        "functionAppName": "helly09180952bec481a5",
        "storageAccountName": "helly09180952bec481a5",
        "appServicePlanName": "helly09180952bec481a5",
        "functionEndpoint": "https://helly09180952bec481a5.azurewebsites.net"
    },
    "fx-resource-local-debug": {
        "trustDevCert": "{{fx-resource-local-debug.trustDevCert}}",
        "skipNgrok": "{{fx-resource-local-debug.skipNgrok}}",
        "localBotEndpoint": "{{fx-resource-local-debug.localBotEndpoint}}"
    },
    "fx-resource-appstudio": {},
    "fx-resource-simple-auth": {
        "endpoint": "https://helly09180952sac481a5.azurewebsites.net"
    }
}